Metadata-Version: 2.1
Name: customTNC-shopify
Version: 12.6.0
Summary: Shopify API for Python
Home-page: https://github.com/Shopify/shopify_python_api
Author: Shopify
Author-email: developers@shopify.com
License: MIT License
Platform: Any
Classifier: Development Status :: 5 - Production/Stable
Classifier: Intended Audience :: Developers
Classifier: License :: OSI Approved :: MIT License
Classifier: Operating System :: OS Independent
Classifier: Programming Language :: Python
Classifier: Programming Language :: Python :: 3
Classifier: Programming Language :: Python :: 3.7
Classifier: Programming Language :: Python :: 3.8
Classifier: Programming Language :: Python :: 3.9
Classifier: Programming Language :: Python :: 3.10
Classifier: Programming Language :: Python :: 3.11
Classifier: Programming Language :: Python :: 3.12
Classifier: Topic :: Software Development
Classifier: Topic :: Software Development :: Libraries
Classifier: Topic :: Software Development :: Libraries :: Python Modules
License-File: LICENSE
Requires-Dist: pyactiveresource>=2.2.2
Requires-Dist: PyJWT>=2.0.0
Requires-Dist: six
Requires-Dist: PyYAML; python_version < "3.12"
Requires-Dist: PyYAML>=6.0.1; python_version >= "3.12"
